{
    "@context": {
        "@base": "https://my.url/models/coordination/",
        "crdn": "https://my.url/metamodels/coordination#",

        "event-loop": { "@id": "crdn:event-loop", "@type": "@id" },
        "has-event": { "@id": "crdn:has-event", "@type": "@id" }
    },
    "@graph": [
        { "@id": "approach-start", "@type": "crdn:Event" },
        { "@id": "approach-end", "@type": "crdn:Event" },
        { "@id": "grasp-start", "@type": "crdn:Event" },
        { "@id": "grasp-end", "@type": "crdn:Event" },
        { "@id": "lift-start", "@type": "crdn:Event" },
        { "@id": "lift-end", "@type": "crdn:Event" },
        { "@id": "pickup-event-loop", "@type": "crdn:EventLoop" },
        {
            "@id": "pickup-event-loop", "@type": "crdn:EventLoopConn",
            "event-loop": "pickup-event-loop",
            "has-event": [
                "approach-start", "approach-end", "grasp-start", "grasp-end", "lift-start", "lift-end"
            ]
        },
        { "@id": "approach-arm1-start", "@type": "crdn:Event" },
        { "@id": "approach-arm1-end", "@type": "crdn:Event" },
        { "@id": "approach-arm2-start", "@type": "crdn:Event" },
        { "@id": "approach-arm2-end", "@type": "crdn:Event" },
        {
            "@id": "dual-arm-pickup-event-loop", "@type": "crdn:EventLoopConn",
            "event-loop": "pickup-event-loop",
            "has-event": [
                "approach-arm1-start", "approach-arm1-end",
                "approach-arm2-start", "approach-arm2-end",
                "grasp-start", "grasp-end", "lift-start", "lift-end"
            ]
        }
    ]
}